geocodertools/__init__.py
geocodertools/reverse.py
geocodertools/misc/README.md
geocodertools-0.1.7.data/scripts/geocodertools
geocodertools-0.1.7.dist-info/METADATA
geocodertools-0.1.7.dist-info/RECORD
geocodertools-0.1.7.dist-info/WHEEL
geocodertools-0.1.7.dist-info/top_level.txt
