Metadata-Version: 2.1
Name: geocodertools
Version: 0.1.7
Summary: Functions to work with Geo coordinates, reverse geo coding and getting city names out of coordinates without internet
Home-page: https://github.com/MartinThoma/geocodertools
Author: Martin Thoma
Author-email: info@martin-thoma.de
Maintainer: Martin Thoma
Maintainer-email: info@martin-thoma.de
License: MIT
Download-URL: https://github.com/MartinThoma/geocodertools
Keywords: geocoder,longitude,latitude
Platform: Linux
Platform: MacOS X
Platform: Windows
Classifier: Development Status :: 7 - Inactive
Classifier: Environment :: Console
Classifier: Intended Audience :: Developers
Classifier: Intended Audience :: Science/Research
Classifier: License :: OSI Approved :: MIT License
Classifier: Natural Language :: English
Classifier: Programming Language :: Python :: 2.7
Classifier: Programming Language :: Python :: 3
Classifier: Programming Language :: Python :: 3.3
Classifier: Programming Language :: Python :: 3.4
Classifier: Topic :: Software Development
Classifier: Topic :: Utilities
Requires-Dist: argparse
Requires-Dist: nose
